agx/__init__.py
agx-2.36.0.0.dist-info/METADATA
agx-2.36.0.0.dist-info/WHEEL
agx-2.36.0.0.dist-info/RECORD
