Metadata-Version: 2.1
Name: agx
Version: 2.36.0.0
Summary: Project containing the AGX Dynamics version that is installed, to support pypi libraries depending on AGX. Will develop into downloading AGX Dynamics itself.
License: Proprietary
Author: Algoryx Simulation
Author-email: contact@algoryx.se
Requires-Python: >=3.8
Classifier: Intended Audience :: Manufacturing
Classifier: Intended Audience :: Science/Research
Classifier: License :: Other/Proprietary License
Classifier: Programming Language :: Python :: 3
Classifier: Programming Language :: Python :: 3.8
Classifier: Programming Language :: Python :: 3.9
Classifier: Programming Language :: Python :: 3.10
Classifier: Programming Language :: Python :: 3.11
Classifier: Topic :: Scientific/Engineering :: Physics
Classifier: Topic :: Scientific/Engineering :: Visualization
